README.md
setup.py
cerberus/__init__.py
cerberus/acl/AbstractService.py
cerberus/acl/AccessControlList.py
cerberus/acl/__init__.py
cerberus/auth/Authenticate.py
cerberus/auth/__init__.py
cerberus/dtos/AuthenticationType.py
cerberus/dtos/Connection.py
cerberus/dtos/Error.py
cerberus/dtos/Role.py
cerberus/dtos/SecurityHash.py
cerberus/dtos/Session.py
cerberus/dtos/User.py
cerberus/dtos/__init__.py
cerberus/entities/__init__.py
cerberus/entities/entities.py
cerberus/exceptions/__init__.py
cerberus/exceptions/exceptions.py
cerberus/management/ConnectionExecuteService.py
cerberus/management/SessionExecuteService.py
cerberus/management/SessionManager.py
cerberus/management/SessionManagerAbstractService.py
cerberus/management/__init__.py
cerberus/mappers/ConnectionMapper.py
cerberus/mappers/HeaderMapper.py
cerberus/mappers/SecurityHashMapper.py
cerberus/mappers/SessionMapper.py
cerberus/mappers/UserMapper.py
cerberus/mappers/__init__.py
cerberus/model/AbstractModelResource.py
cerberus/model/KsmClientModel.py
cerberus/model/KsmConnectionModel.py
cerberus/model/KsmRoleUserModel.py
cerberus/model/KsmSecurityModel.py
cerberus/model/KsmServiceModel.py
cerberus/model/KsmSessionModel.py
cerberus/model/KsmUserModel.py
cerberus/model/ParentModel.py
cerberus/model/__init__.py
cerberus/requests/BodyRQ.py
cerberus/requests/CreateUserAccessTokenRQ.py
cerberus/requests/CreateUserRQ.py
cerberus/requests/HeaderRQ.py
cerberus/requests/LoginUserRQ.py
cerberus/requests/Request.py
cerberus/requests/__init__.py
cerberus/responses/BodyRS.py
cerberus/responses/CreateUserAccessTokenRS.py
cerberus/responses/CreateUserRS.py
cerberus/responses/FirebaseUserRS.py
cerberus/responses/HeaderRS.py
cerberus/responses/LoginClientRS.py
cerberus/responses/Response.py
cerberus/responses/SessionRS.py
cerberus/responses/__init__.py
cerberus/services/AbstractService.py
cerberus/services/ConnectionService.py
cerberus/services/FirebaseService.py
cerberus/services/SecurityHashService.py
kea_cerberus.egg-info/PKG-INFO
kea_cerberus.egg-info/SOURCES.txt
kea_cerberus.egg-info/dependency_links.txt
kea_cerberus.egg-info/not-zip-safe
kea_cerberus.egg-info/top_level.txt