Metadata-Version: 1.0
Name: kea-cerberus
Version: 1.1.9
Summary: Control client, users and service execution of your projects in python
Home-page: http://kea.mx/
Author: Cesar Ocotitla
Author-email: cesar@kea.mx
License: MIT
Platform: UNKNOWN
